prvict/__init__.py
prvict/main.py
prvict-0.8.5.dist-info/LICENSE
prvict-0.8.5.dist-info/METADATA
prvict-0.8.5.dist-info/WHEEL
prvict-0.8.5.dist-info/top_level.txt
prvict-0.8.5.dist-info/RECORD
