Metadata-Version: 2.1
Name: prvict
Version: 0.8.5
Summary: A library pioneering AI and computational based tech solutions.
Home-page: https://github.com/VaidikKhurana/prvict
Author: Vaidik Khurana
Author-email: vaidikkhurana@gmail.com
Project-URL: Bug Tracker, https://github.com/VaidikKhurana/prvict/issues
Classifier: Programming Language :: Python :: 3
Classifier: License :: OSI Approved :: MIT License
Classifier: Operating System :: OS Independent
Requires-Python: >=3.11
License-File: LICENSE
